Workbook

Sheet All_Top_5
A1: Protein_name | B1: Target_group | C1: Uniprot_id | D1: Target_name | E1: Target_type | F1: Complex_participants | G1: intracluster_score | H1: intercluster_score | I1: Conectivity_score | J1: Source | K1: Cluster
A2: FUCA1 | B2: =VLOOKUP(Tabla6[[#This Row],[Protein_name]],raw!$A$2:$F$5391,6,FALSE) -> T4 | C2: =VLOOKUP(Tabla6[[#This Row],[Protein_name]],raw!$A$2:$F$5391,4,FALSE) -> P04066 | D2: =VLOOKUP(Tabla6[[#This Row],[Protein_name]],raw!$A$2:$F$5391,2,FALSE) -> tissue alpha-l-fucosidase (ec 3.2.1.51) (alpha-l-fucosidase i) (alpha-l-fucoside fucohydrolase 1) (alpha-l-fucosidase 1) | E2: =VLOOKUP(Tabla6[[#This Row],[Protein_name]],raw!$A$2:$F$5391,5,FALSE) -> SINGLE PROTEIN | F2: =VLOOKUP(Tabla6[[#This Row],[Protein_name]],raw!$A$2:$F$5391,3,FALSE) -> 0 | G2: =VLOOKUP(Tabla6[[#This Row],[Protein_name]],T4_metrics!$A$2:$G$693,4,FALSE) -> 6.779 | H2: =VLOOKUP(Tabla6[[#This Row],[Protein_name]],T4_metrics!$A$2:$G$693,5,FALSE) -> 1.598 | I2: =VLOOKUP(Tabla6[[#This Row],[Protein_name]],T4_metrics!$A$2:$G$693,6,FALSE) -> 0.74878415 | J2: Connectivity | K2: 0
A3: IDUA | B3: =VLOOKUP(Tabla6[[#This Row],[Protein_name]],raw!$A$2:$F$5391,6,FALSE) -> T4 | C3: =VLOOKUP(Tabla6[[#This Row],[Protein_name]],raw!$A$2:$F$5391,4,FALSE) -> P35475 | D3: =VLOOKUP(Tabla6[[#This Row],[Protein_name]],raw!$A$2:$F$5391,2,FALSE) -> alpha-l-iduronidase (ec 3.2.1.76) | E3: =VLOOKUP(Tabla6[[#This Row],[Protein_name]],raw!$A$2:$F$5391,5,FALSE) -> SINGLE PROTEIN | F3: =VLOOKUP(Tabla6[[#This Row],[Protein_name]],raw!$A$2:$F$5391,3,FALSE) -> 0 | G3: =VLOOKUP(Tabla6[[#This Row],[Protein_name]],T4_metrics!$A$2:$G$693,4,FALSE) -> 8.268 | H3: =VLOOKUP(Tabla6[[#This Row],[Protein_name]],T4_metrics!$A$2:$G$693,5,FALSE) -> 0.448 | I3: =VLOOKUP(Tabla6[[#This Row],[Protein_name]],T4_metrics!$A$2:$G$693,6,FALSE) -> 0.72258046 | J3: Connectivity | K3: 0
A4: NEU1 | B4: =VLOOKUP(Tabla6[[#This Row],[Protein_name]],raw!$A$2:$F$5391,6,FALSE) -> T4 | C4: =VLOOKUP(Tabla6[[#This Row],[Protein_name]],raw!$A$2:$F$5391,4,FALSE) -> Q99519 | D4: =VLOOKUP(Tabla6[[#This Row],[Protein_name]],raw!$A$2:$F$5391,2,FALSE) -> sialidase-1 (ec 3.2.1.18) (acetylneuraminyl hydrolase) (g9 sialidase) (lysosomal sialidase) (n-acetyl-alpha-neuraminidase 1) | E4: =VLOOKUP(Tabla6[[#This Row],[Protein_name]],raw!$A$2:$F$5391,5,FALSE) -> SINGLE PROTEIN | F4: =VLOOKUP(Tabla6[[#This Row],[Protein_name]],raw!$A$2:$F$5391,3,FALSE) -> 0 | G4: =VLOOKUP(Tabla6[[#This Row],[Protein_name]],T4_metrics!$A$2:$G$693,4,FALSE) -> 4.565 | H4: =VLOOKUP(Tabla6[[#This Row],[Protein_name]],T4_metrics!$A$2:$G$693,5,FALSE) -> 0 | I4: =VLOOKUP(Tabla6[[#This Row],[Protein_name]],T4_metrics!$A$2:$G$693,6,FALSE) -> 0.70894846 | J4: Connectivity | K4: 0
A5: MAN2B1 | B5: =VLOOKUP(Tabla6[[#This Row],[Protein_name]],raw!$A$2:$F$5391,6,FALSE) -> T4 | C5: =VLOOKUP(Tabla6[[#This Row],[Protein_name]],raw!$A$2:$F$5391,4,FALSE) -> O00754 | D5: =VLOOKUP(Tabla6[[#This Row],[Protein_name]],raw!$A$2:$F$5391,2,FALSE) -> lysosomal alpha-mannosidase (laman) (ec 3.2.1.24) (lysosomal acid alpha-mannosidase) (mannosidase alpha class 2b member 1) (mannosidase alpha-b) [cleaved into: lysosomal alpha-mannosidase a peptide; lysosomal alpha-mannosidase b peptide; lysosomal alpha-mannosidase c peptide; lysosomal alpha-mannosidase d peptide; lysosomal alpha-mannosidase e peptide] | E5: =VLOOKUP(Tabla6[[#This Row],[Protein_name]],raw!$A$2:$F$5391,5,FALSE) -> SINGLE PROTEIN | F5: =VLOOKUP(Tabla6[[#This Row],[Protein_name]],raw!$A$2:$F$5391,3,FALSE) -> 0 | G5: =VLOOKUP(Tabla6[[#This Row],[Protein_name]],T4_metrics!$A$2:$G$693,4,FALSE) -> 6.809 | H5: =VLOOKUP(Tabla6[[#This Row],[Protein_name]],T4_metrics!$A$2:$G$693,5,FALSE) -> 0 | I5: =VLOOKUP(Tabla6[[#This Row],[Protein_name]],T4_metrics!$A$2:$G$693,6,FALSE) -> 0.70880052 | J5: Connectivity | K5: 0
A6: NAGLU | B6: =VLOOKUP(Tabla6[[#This Row],[Protein_name]],raw!$A$2:$F$5391,6,FALSE) -> T4 | C6: =VLOOKUP(Tabla6[[#This Row],[Protein_name]],raw!$A$2:$F$5391,4,FALSE) -> P54802 | D6: =VLOOKUP(Tabla6[[#This Row],[Protein_name]],raw!$A$2:$F$5391,2,FALSE) -> alpha-n-acetylglucosaminidase (ec 3.2.1.50) (n-acetyl-alpha-glucosaminidase) (nag) [cleaved into: alpha-n-acetylglucosaminidase 82 kda form; alpha-n-acetylglucosaminidase 77 kda form] | E6: =VLOOKUP(Tabla6[[#This Row],[Protein_name]],raw!$A$2:$F$5391,5,FALSE) -> SINGLE PROTEIN | F6: =VLOOKUP(Tabla6[[#This Row],[Protein_name]],raw!$A$2:$F$5391,3,FALSE) -> 0 | G6: =VLOOKUP(Tabla6[[#This Row],[Protein_name]],T4_metrics!$A$2:$G$693,4,FALSE) -> 10.574 | H6: =VLOOKUP(Tabla6[[#This Row],[Protein_name]],T4_metrics!$A$2:$G$693,5,FALSE) -> 0 | I6: =VLOOKUP(Tabla6[[#This Row],[Protein_name]],T4_metrics!$A$2:$G$693,6,FALSE) -> 0.6790441 | J6: Connectivity | K6: 0
A7: CPX-5675 | B7: =VLOOKUP(Tabla6[[#This Row],[Protein_name]],raw!$A$2:$F$5391,6,FALSE) -> T4 | C7: =VLOOKUP(Tabla6[[#This Row],[Protein_name]],raw!$A$2:$F$5391,4,FALSE) -> P06681, P0C0L4, P0C0L4, P0C0L4 | D7: =VLOOKUP(Tabla6[[#This Row],[Protein_name]],raw!$A$2:$F$5391,2,FALSE) -> complement c2 (ec 3.4.21.43) (c3/c5 convertase) [cleaved into: complement c2b fragment; complement c2a fragment] | E7: =VLOOKUP(Tabla6[[#This Row],[Protein_name]],raw!$A$2:$F$5391,5,FALSE) -> PROTEIN COMPLEX | F7: =VLOOKUP(Tabla6[[#This Row],[Protein_name]],raw!$A$2:$F$5391,3,FALSE) -> P06681-PRO_0000027612,P0C0L4-PRO_0000005970,P0C0L4-PRO_0000005966,P0C0L4-PRO_0000005972 | G7: =VLOOKUP(Tabla6[[#This Row],[Protein_name]],T4_metrics!$A$2:$G$693,4,FALSE) -> 23.405 | H7: =VLOOKUP(Tabla6[[#This Row],[Protein_name]],T4_metrics!$A$2:$G$693,5,FALSE) -> 0.865 | I7: =VLOOKUP(Tabla6[[#This Row],[Protein_name]],T4_metrics!$A$2:$G$693,6,FALSE) -> 1.5475136 | J7: Connectivity | K7: 1
A8: CPX-6215 | B8: =VLOOKUP(Tabla6[[#This Row],[Protein_name]],raw!$A$2:$F$5391,6,FALSE) -> T4 | C8: =VLOOKUP(Tabla6[[#This Row],[Protein_name]],raw!$A$2:$F$5391,4,FALSE) -> P00742, P00742 | D8: =VLOOKUP(Tabla6[[#This Row],[Protein_name]],raw!$A$2:$F$5391,2,FALSE) -> coagulation factor x (ec 3.4.21.6) (stuart factor) (stuart-prower factor) [cleaved into: factor x light chain; factor x heavy chain; activated factor xa heavy chain] | E8: =VLOOKUP(Tabla6[[#This Row],[Protein_name]],raw!$A$2:$F$5391,5,FALSE) -> PROTEIN COMPLEX | F8: =VLOOKUP(Tabla6[[#This Row],[Protein_name]],raw!$A$2:$F$5391,3,FALSE) -> P00742-PRO_0000027789,P00742-PRO_0000027788 | G8: =VLOOKUP(Tabla6[[#This Row],[Protein_name]],T4_metrics!$A$2:$G$693,4,FALSE) -> 19.108 | H8: =VLOOKUP(Tabla6[[#This Row],[Protein_name]],T4_metrics!$A$2:$G$693,5,FALSE) -> 0.941 | I8: =VLOOKUP(Tabla6[[#This Row],[Protein_name]],T4_metrics!$A$2:$G$693,6,FALSE) -> 1.4572379 | J8: Connectivity | K8: 1
A9: CPX-6234 | B9: =VLOOKUP(Tabla6[[#This Row],[Protein_name]],raw!$A$2:$F$5391,6,FALSE) -> T4 | C9: =VLOOKUP(Tabla6[[#This Row],[Protein_name]],raw!$A$2:$F$5391,4,FALSE) -> P03952, P03952 | D9: =VLOOKUP(Tabla6[[#This Row],[Protein_name]],raw!$A$2:$F$5391,2,FALSE) -> plasma kallikrein (ec 3.4.21.34) (fletcher factor) (kininogenin) (plasma prekallikrein) (pkk) [cleaved into: plasma kallikrein heavy chain; plasma kallikrein light chain] | E9: =VLOOKUP(Tabla6[[#This Row],[Protein_name]],raw!$A$2:$F$5391,5,FALSE) -> PROTEIN COMPLEX | F9: =VLOOKUP(Tabla6[[#This Row],[Protein_name]],raw!$A$2:$F$5391,3,FALSE) -> P03952-PRO_0000028022,P03952-PRO_0000028021 | G9: =VLOOKUP(Tabla6[[#This Row],[Protein_name]],T4_metrics!$A$2:$G$693,4,FALSE) -> 17.858 | H9: =VLOOKUP(Tabla6[[#This Row],[Protein_name]],T4_metrics!$A$2:$G$693,5,FALSE) -> 1.081 | I9: =VLOOKUP(Tabla6[[#This Row],[Protein_name]],T4_metrics!$A$2:$G$693,6,FALSE) -> 1.4558477 | J9: Connectivity | K9: 1
A10: CPX-4945 | B10: =VLOOKUP(Tabla6[[#This Row],[Protein_name]],raw!$A$2:$F$5391,6,FALSE) -> T4 | C10: =VLOOKUP(Tabla6[[#This Row],[Protein_name]],raw!$A$2:$F$5391,4,FALSE) -> P00740, P00740 | D10: =VLOOKUP(Tabla6[[#This Row],[Protein_name]],raw!$A$2:$F$5391,2,FALSE) -> coagulation factor ix (ec 3.4.21.22) (christmas factor) (plasma thromboplastin component) (ptc) [cleaved into: coagulation factor ixa light chain; coagulation factor ixa heavy chain] | E10: =VLOOKUP(Tabla6[[#This Row],[Protein_name]],raw!$A$2:$F$5391,5,FALSE) -> PROTEIN COMPLEX | F10: =VLOOKUP(Tabla6[[#This Row],[Protein_name]],raw!$A$2:$F$5391,3,FALSE) -> P00740-PRO_0000027757,P00740-PRO_0000027759 | G10: =VLOOKUP(Tabla6[[#This Row],[Protein_name]],T4_metrics!$A$2:$G$693,4,FALSE) -> 19.111 | H10: =VLOOKUP(Tabla6[[#This Row],[Protein_name]],T4_metrics!$A$2:$G$693,5,FALSE) -> 4.126 | I10: =VLOOKUP(Tabla6[[#This Row],[Protein_name]],T4_metrics!$A$2:$G$693,6,FALSE) -> 1.3763838 | J10: Connectivity | K10: 1
A11: CPX-6224 | B11: =VLOOKUP(Tabla6[[#This Row],[Protein_name]],raw!$A$2:$F$5391,6,FALSE) -> T4 | C11: =VLOOKUP(Tabla6[[#This Row],[Protein_name]],raw!$A$2:$F$5391,4,FALSE) -> P04070, P04070 | D11: =VLOOKUP(Tabla6[[#This Row],[Protein_name]],raw!$A$2:$F$5391,2,FALSE) -> vitamin k-dependent protein c (ec 3.4.21.69) (anticoagulant protein c) (autoprothrombin iia) (blood coagulation factor xiv) [cleaved into: vitamin k-dependent protein c light chain; vitamin k-dependent protein c heavy chain; activation peptide] | E11: =VLOOKUP(Tabla6[[#This Row],[Protein_name]],raw!$A$2:$F$5391,5,FALSE) -> PROTEIN COMPLEX | F11: =VLOOKUP(Tabla6[[#This Row],[Protein_name]],raw!$A$2:$F$5391,3,FALSE) -> P04070-PRO_0000028110,P04070-PRO_0000028109 | G11: =VLOOKUP(Tabla6[[#This Row],[Protein_name]],T4_metrics!$A$2:$G$693,4,FALSE) -> 16.428 | H11: =VLOOKUP(Tabla6[[#This Row],[Protein_name]],T4_metrics!$A$2:$G$693,5,FALSE) -> 0 | I11: =VLOOKUP(Tabla6[[#This Row],[Protein_name]],T4_metrics!$A$2:$G$693,6,FALSE) -> 1.3505542 | J11: Connectivity | K11: 1
A12: NRL | B12: =VLOOKUP(Tabla6[[#This Row],[Protein_name]],raw!$A$2:$F$5391,6,FALSE) -> T4 | C12: =VLOOKUP(Tabla6[[#This Row],[Protein_name]],raw!$A$2:$F$5391,4,FALSE) -> P54845 | D12: =VLOOKUP(Tabla6[[#This Row],[Protein_name]],raw!$A$2:$F$5391,2,FALSE) -> neural retina-specific leucine zipper protein (nrl) | E12: =VLOOKUP(Tabla6[[#This Row],[Protein_name]],raw!$A$2:$F$5391,5,FALSE) -> SINGLE PROTEIN | F12: =VLOOKUP(Tabla6[[#This Row],[Protein_name]],raw!$A$2:$F$5391,3,FALSE) -> 0 | G12: =VLOOKUP(Tabla6[[#This Row],[Protein_name]],T4_metrics!$A$2:$G$693,4,FALSE) -> 28.493 | H12: =VLOOKUP(Tabla6[[#This Row],[Protein_name]],T4_metrics!$A$2:$G$693,5,FALSE) -> 0.553 | I12: =VLOOKUP(Tabla6[[#This Row],[Protein_name]],T4_metrics!$A$2:$G$693,6,FALSE) -> 0.77451374 | J12: Connectivity | K12: 2
A13: GUCY2D | B13: =VLOOKUP(Tabla6[[#This Row],[Protein_name]],raw!$A$2:$F$5391,6,FALSE) -> T4 | C13: =VLOOKUP(Tabla6[[#This Row],[Protein_name]],raw!$A$2:$F$5391,4,FALSE) -> Q02846 | D13: =VLOOKUP(Tabla6[[#This Row],[Protein_name]],raw!$A$2:$F$5391,2,FALSE) -> retinal guanylyl cyclase 1 (retgc-1) (ec 4.6.1.2) (cg-e) (guanylate cyclase 2d, retinal) (rod outer segment membrane guanylate cyclase) (ros-gc) | E13: =VLOOKUP(Tabla6[[#This Row],[Protein_name]],raw!$A$2:$F$5391,5,FALSE) -> SINGLE PROTEIN | F13: =VLOOKUP(Tabla6[[#This Row],[Protein_name]],raw!$A$2:$F$5391,3,FALSE) -> 0 | G13: =VLOOKUP(Tabla6[[#This Row],[Protein_name]],T4_metrics!$A$2:$G$693,4,FALSE) -> 33.858 | H13: =VLOOKUP(Tabla6[[#This Row],[Protein_name]],T4_metrics!$A$2:$G$693,5,FALSE) -> 2.511 | I13: =VLOOKUP(Tabla6[[#This Row],[Protein_name]],T4_metrics!$A$2:$G$693,6,FALSE) -> 0.73510789 | J13: Connectivity | K13: 2
... A181: CPX-7519 | B181: =VLOOKUP(Tabla6[[#This Row],[Protein_name]],raw!$A$2:$F$5391,6,FALSE) -> T4 | C181: =VLOOKUP(Tabla6[[#This Row],[Protein_name]],raw!$A$2:$F$5391,4,FALSE) -> P35227, Q99496, Q14781, P78364 | D181: =VLOOKUP(Tabla6[[#This Row],[Protein_name]],raw!$A$2:$F$5391,2,FALSE) -> chromobox protein homolog 2 | E181: =VLOOKUP(Tabla6[[#This Row],[Protein_name]],raw!$A$2:$F$5391,5,FALSE) -> PROTEIN COMPLEX | F181: =VLOOKUP(Tabla6[[#This Row],[Protein_name]],raw!$A$2:$F$5391,3,FALSE) -> PCGF2,RNF2,CBX2,PHC1 | G181: =VLOOKUP(Tabla6[[#This Row],[Protein_name]],T4_metrics!$A$2:$G$693,4,FALSE) -> 108.916 | H181: =VLOOKUP(Tabla6[[#This Row],[Protein_name]],T4_metrics!$A$2:$G$693,5,FALSE) -> 40.809 | I181: =VLOOKUP(Tabla6[[#This Row],[Protein_name]],T4_metrics!$A$2:$G$693,6,FALSE) -> 0.93053891 | J181: Intracluster | K181: 11

Sheet connectivity
A1: protein_name | B1: Clúster | C1: connectivity_score | D1: go_term
A2: FUCA1 | B2: 0 | C2: 0.74878415 | D2: Lysosomal Lumen
A3: IDUA | B3: 0 | C3: 0.72258046 | D3: Lysosomal Lumen
A4: NEU1 | B4: 0 | C4: 0.70894846 | D4: Lysosomal Lumen
A5: MAN2B1 | B5: 0 | C5: 0.70880052 | D5: Lysosomal Lumen
A6: NAGLU | B6: 0 | C6: 0.6790441 | D6: Lysosomal Lumen
A7: CPX-5675 | B7: 1 | C7: 1.5475136 | D7: Regulation Of Opsonization
A8: CPX-6215 | B8: 1 | C8: 1.4572379 | D8: Regulation Of Opsonization
A9: CPX-6234 | B9: 1 | C9: 1.4558477 | D9: Regulation Of Opsonization
A10: CPX-4945 | B10: 1 | C10: 1.3763838 | D10: Regulation Of Opsonization
A11: CPX-6224 | B11: 1 | C11: 1.3505542 | D11: Regulation Of Opsonization
A12: NRL | B12: 2 | C12: 0.77451374 | D12: Visual Perception
A13: GUCY2D | B13: 2 | C13: 0.73510789 | D13: Visual Perception
... A61: CPX-2296 | B61: 11 | C61: 1.0316847 | D61: PRC1 Complex

Sheet intercluster
A1: protein_name | B1: Clúster | C1: Intercluster_Connect_Score | D1: go_term
A2: FUCA1 | B2: 0 | C2: 1.598 | D2: Lysosomal Lumen
A3: IDS | B3: 0 | C3: 1.158 | D3: Lysosomal Lumen
A4: ARSB | B4: 0 | C4: 1.031 | D4: Lysosomal Lumen
A5: B4GALNT1 | B5: 0 | C5: 0.871 | D5: Lysosomal Lumen
A6: SGSH | B6: 0 | C6: 0.463 | D6: Lysosomal Lumen
A7: CPX-4945 | B7: 1 | C7: 4.126 | D7: Regulation Of Opsonization
A8: CPX-6223 | B8: 1 | C8: 4.086 | D8: Regulation Of Opsonization
A9: ADAMTS13 | B9: 1 | C9: 2.949 | D9: Regulation Of Opsonization
A10: SERPING1 | B10: 1 | C10: 1.874 | D10: Regulation Of Opsonization
A11: CPX-5602 | B11: 1 | C11: 1.618 | D11: Regulation Of Opsonization
A12: RPE65 | B12: 2 | C12: 17.32 | D12: Visual Perception
A13: CNGB1 | B13: 2 | C13: 11.184 | D13: Visual Perception
... A61: CPX-2297 | B61: 11 | C61: 52.128 | D61: PRC1 Complex

Sheet intracluster
A1: protein_name | B1: Clúster | C1: Intracluster_Connect_Score | D1: go_term
A2: GNS | B2: 0 | C2: 10.585 | D2: Lysosomal Lumen
A3: NAGLU | B3: 0 | C3: 10.574 | D3: Lysosomal Lumen
A4: CPX-502 | B4: 0 | C4: 9.758 | D4: Lysosomal Lumen
A5: CPX-687 | B5: 0 | C5: 9.7 | D5: Lysosomal Lumen
A6: CPX-686 | B6: 0 | C6: 9.195 | D6: Lysosomal Lumen
A7: CPX-6239 | B7: 1 | C7: 27.508 | D7: Regulation Of Opsonization
A8: CPX-6165 | B8: 1 | C8: 26.476 | D8: Regulation Of Opsonization
A9: SERPING1 | B9: 1 | C9: 25.392 | D9: Regulation Of Opsonization
A10: CPX-6179 | B10: 1 | C10: 25.254 | D10: Regulation Of Opsonization
A11: CPX-6240 | B11: 1 | C11: 25.052 | D11: Regulation Of Opsonization
A12: CRX | B12: 2 | C12: 37.587 | D12: Visual Perception
A13: RPE65 | B13: 2 | C13: 37.172 | D13: Visual Perception
... A61: CPX-7519 | B61: 11 | C61: 108.916 | D61: PRC1 Complex

Sheet raw
A1: Node_id | B1: Target_name | C1: Complex_participants | D1: Uniprot_id | E1: Target_type | F1: Target_group | G1: Source_db | H1: Target_group_score | I1: Target_group_score_normalized | J1: Conectivity_Score | K1: Disease
A2: CPX-289 | B2: glutamate nmda receptor; grin1/grin2a | C2: GRIN2D,GRIN1 | D2: O15399, Q05586 | E2: PROTEIN COMPLEX | F2: T1, T2, T3, T4 | G2: ChEMBL, STRING, TTD | H2: 16.1 | I2: 1 | K2: Alzheimer's Disease
A3: CPX-659 | B3: dna replication factor cdt1 (double parked homolog) (dup) | C3: CDT1,GMNN | D3: Q9H211, O75496 | E3: PROTEIN COMPLEX | F3: T1, T2, T3, T4 | G3: ChEMBL, STRING | H3: 16.1 | I3: 1 | K3: Alzheimer's Disease
A4: CPX-661 | B4: geminin | C4: GMNN,MCIDAS | D4: O75496, D6RGH6 | E4: PROTEIN COMPLEX | F4: T1, T2, T3, T4 | G4: ChEMBL, STRING | H4: 16.1 | I4: 1 | K4: Alzheimer's Disease
A5: CPX-702 | B5: nuclear receptor coactivator 2 (ncoa-2) (class e basic helix-loop-helix protein 75) (bhlhe75) (transcriptional intermediary factor 2) (htif2) | C5: NCOA2,PPARG | D5: Q15596, P37231 | E5: PROTEIN COMPLEX | F5: T1, T2, T3, T4 | G5: ChEMBL, STRING, TTD | H5: 16.1 | I5: 1 | K5: Alzheimer's Disease
A6: CPX-711 | B6: nuclear receptor coactivator 1 (ncoa-1) (ec 2.3.1.48) (class e basic helix-loop-helix protein 74) (bhlhe74) (protein hin-2) (rip160) (renal carcinoma antigen ny-ren-52) (steroid receptor coactivator 1) (src-1) | C6: NCOA1,PPARG | D6: Q15788, P37231 | E6: PROTEIN COMPLEX | F6: T1, T2, T3, T4 | G6: ChEMBL, STRING, TTD | H6: 16.1 | I6: 1 | K6: Alzheimer's Disease
A7: CPX-793 | B7: aprataxin (ec 3.6.1.71) (ec 3.6.1.72) (forkhead-associated domain histidine triad-like protein) (fha-hit) | C7: LIG3,XRCC1,TDP1,APLF,POLB,APTX,PNKP | D7: P49916, P18887, Q9NUW8, Q8IW19, P06746, Q7Z2E3, Q96T60 | E7: PROTEIN COMPLEX | F7: T1, T2, T3, T4 | G7: ChEMBL, STRING | H7: 16.1 | I7: 1 | K7: Alzheimer's Disease
A8: CPX-6094 | B8: geminin | C8: GMNN,HOXD10 | D8: O75496, P28358 | E8: PROTEIN COMPLEX | F8: T1, T2, T3, T4 | G8: ChEMBL, STRING | H8: 16.1 | I8: 1 | K8: Alzheimer's Disease
A9: ACHE | B9: acetylcholinesterase | D9: P22303 | E9: SINGLE PROTEIN | F9: T1, T2, T3 | G9: ChEMBL, TTD | H9: 16 | I9: 0.994375 | K9: Alzheimer's Disease
A10: CBX1 | B10: chromobox protein homolog 1 | D10: P83916 | E10: SINGLE PROTEIN | F10: T1, T2, T3 | G10: ChEMBL | H10: 16 | I10: 0.994375 | K10: Alzheimer's Disease
A11: CPX-285 | B11: glutamate [nmda] receptor subunit epsilon 2 | C11: GRIN2B,GRIN1 | D11: Q13224, Q05586 | E11: PROTEIN COMPLEX | F11: T1, T2, T3 | G11: ChEMBL, TTD | H11: 16 | I11: 0.994375 | K11: Alzheimer's Disease
A12: CPX-286 | B12: glutamate nmda receptor; grin1/grin2a | C12: GRIN1,GRIN2C | D12: Q05586, Q14957 | E12: PROTEIN COMPLEX | F12: T1, T2, T3 | G12: ChEMBL, TTD | H12: 16 | I12: 0.994375 | K12: Alzheimer's Disease
A13: CPX-294 | B13: glutamate [nmda] receptor subunit epsilon 2 | C13: GRIN1,GRIN2A,GRIN2B | D13: Q05586, Q12879, Q13224 | E13: PROTEIN COMPLEX | F13: T1, T2, T3 | G13: ChEMBL, TTD | H13: 16 | I13: 0.994375 | K13: Alzheimer's Disease
A14: CPX-660 | B14: geminin | C14: GMNN,HOXC9 | D14: O75496, P31274 | E14: PROTEIN COMPLEX | F14: T1, T2, T3 | G14: ChEMBL | H14: 16 | I14: 0.994375 | K14: Alzheimer's Disease
A15: CPX-1062 | B15: amyloid beta a4 protein (app) | C15: P05067-PRO_0000000092,P05067-PRO_0000000093 | D15: P05067, P05067 | E15: PROTEIN COMPLEX | F15: T1, T2, T3 | G15: ChEMBL, TTD | H15: 16 | I15: 0.994375 | K15: Alzheimer's Disease
A16: CPX-1069 | B16: amyloid beta a4 protein (app) | C16: P05067-PRO_0000000093 | D16: P05067 | E16: PROTEIN COMPLEX | F16: T1, T2, T3 | G16: ChEMBL, TTD | H16: 16 | I16: 0.994375 | K16: Alzheimer's Disease
A17: CPX-1070 | B17: amyloid beta a4 protein (app) | C17: P05067-PRO_0000000092 | D17: P05067 | E17: PROTEIN COMPLEX | F17: T1, T2, T3 | G17: ChEMBL, TTD | H17: 16 | I17: 0.994375 | K17: Alzheimer's Disease
A18: CPX-1120 | B18: amyloid beta a4 protein (app) | C18: P05067-PRO_0000000092,P05067-PRO_0000000093 | D18: P05067, P05067 | E18: PROTEIN COMPLEX | F18: T1, T2, T3 | G18: ChEMBL, TTD | H18: 16 | I18: 0.994375 | K18: Alzheimer's Disease
A19: CPX-1134 | B19: amyloid beta a4 protein (app) | C19: P05067-PRO_0000000092 | D19: P05067 | E19: PROTEIN COMPLEX | F19: T1, T2, T3 | G19: ChEMBL, TTD | H19: 16 | I19: 0.994375 | K19: Alzheimer's Disease
A20: CPX-1180 | B20: amyloid beta a4 protein (app) | C20: P05067-PRO_0000000093 | D20: P05067 | E20: PROTEIN COMPLEX | F20: T1, T2, T3 | G20: ChEMBL, TTD | H20: 16 | I20: 0.994375 | K20: Alzheimer's Disease
A21: CPX-2202 | B21: glutamate nmda receptor; grin1/grin2a | C21: GRIN1,GRIN2A | D21: Q05586, Q12879 | E21: PROTEIN COMPLEX | F21: T1, T2, T3 | G21: ChEMBL, TTD | H21: 16 | I21: 0.994375 | K21: Alzheimer's Disease
A22: DRD2 | B22: dopamine d2 receptor | D22: P14416 | E22: SINGLE PROTEIN | F22: T1, T2, T3 | G22: ChEMBL, TTD | H22: 16 | I22: 0.994375 | K22: Alzheimer's Disease
A23: EHMT2 | B23: histone-lysine n-methyltransferase, h3 lysine-9 specific 3 | D23: Q96KQ7 | E23: SINGLE PROTEIN | F23: T1, T2, T3 | G23: ChEMBL | H23: 16 | I23: 0.994375 | K23: Alzheimer's Disease
A24: HRH3 | B24: histamine h3 receptor | D24: Q9Y5N1 | E24: SINGLE PROTEIN | F24: T1, T2, T3 | G24: ChEMBL, TTD | H24: 16 | I24: 0.994375 | K24: Alzheimer's Disease
A25: KDM4E | B25: lysine-specific demethylase 4d-like | D25: B2RXH2 | E25: SINGLE PROTEIN | F25: T1, T2, T3 | G25: ChEMBL | H25: 16 | I25: 0.994375 | K25: Alzheimer's Disease
A26: LMNA | B26: prelamin-a/c | D26: P02545 | E26: SINGLE PROTEIN | F26: T1, T2, T3 | G26: ChEMBL | H26: 16 | I26: 0.994375 | K26: Alzheimer's Disease
A27: SLC6A4 | B27: serotonin transporter | D27: P31645 | E27: SINGLE PROTEIN | F27: T1, T2, T3 | G27: ChEMBL, TTD | H27: 16 | I27: 0.994375 | K27: Alzheimer's Disease
A28: SLCO1B1 | B28: solute carrier organic anion transporter family member 1b1 | D28: Q9Y6L6 | E28: SINGLE PROTEIN | F28: T1, T2, T3 | G28: ChEMBL | H28: 16 | I28: 0.994375 | K28: Alzheimer's Disease
A29: SLCO1B3 | B29: solute carrier organic anion transporter family member 1b3 | D29: Q9NPD5 | E29: SINGLE PROTEIN | F29: T1, T2, T3 | G29: ChEMBL | H29: 16 | I29: 0.994375 | K29: Alzheimer's Disease
A30: USP1 | B30: ubiquitin carboxyl-terminal hydrolase 1 | D30: O94782 | E30: SINGLE PROTEIN | F30: T1, T2, T3 | G30: ChEMBL | H30: 16 | I30: 0.994375 | K30: Alzheimer's Disease
A31: BCHE | B31: butyrylcholinesterase | D31: P06276 | E31: SINGLE PROTEIN | F31: T1, T2 | G31: ChEMBL, TTD | H31: 15 | I31: 0.938125 | K31: Alzheimer's Disease
A32: CPX-255 | B32: acetylcholine receptor protein epsilon chain | C32: CHRND,Q04844-PRO_0000000329,P02708-PRO_0000000305,P11230-PRO_0000000315 | D32: Q07001, Q04844, P02708, P11230 | E32: PROTEIN COMPLEX | F32: T1, T2 | G32: ChEMBL | H32: 15 | I32: 0.938125 | K32: Alzheimer's Disease
A33: DYRK1A | B33: dual-specificity tyrosine-phosphorylation regulated kinase 1a | D33: Q13627 | E33: SINGLE PROTEIN | F33: T1, T2 | G33: ChEMBL | H33: 15 | I33: 0.938125 | K33: Alzheimer's Disease
A34: DYRK2 | B34: dual-specificity tyrosine-phosphorylation regulated kinase 2 | D34: Q92630 | E34: SINGLE PROTEIN | F34: T1, T2 | G34: ChEMBL | H34: 15 | I34: 0.938125 | K34: Alzheimer's Disease
A35: IDH1 | B35: isocitrate dehydrogenase [nadp] cytoplasmic | D35: O75874 | E35: SINGLE PROTEIN | F35: T1, T2 | G35: ChEMBL | H35: 15 | I35: 0.938125 | K35: Alzheimer's Disease
A36: NPSR1 | B36: neuropeptide s receptor | D36: Q6W5P4 | E36: SINGLE PROTEIN | F36: T1, T2 | G36: ChEMBL | H36: 15 | I36: 0.938125 | K36: Alzheimer's Disease
A37: PMP22 | B37: peripheral myelin protein 22 | D37: Q01453 | E37: SINGLE PROTEIN | F37: T1, T2 | G37: ChEMBL | H37: 15 | I37: 0.938125 | K37: Alzheimer's Disease
A38: PTH1R | B38: parathyroid hormone receptor | D38: Q03431 | E38: SINGLE PROTEIN | F38: T1, T2 | G38: ChEMBL | H38: 15 | I38: 0.938125 | K38: Alzheimer's Disease
A39: TRPV1 | B39: vanilloid receptor | D39: Q8NER1 | E39: SINGLE PROTEIN | F39: T1, T2 | G39: ChEMBL | H39: 15 | I39: 0.938125 | K39: Alzheimer's Disease
A40: CPX-1 | B40: mothers against decapentaplegic homolog 2 | C40: SMAD4,SMAD2,SMAD3 | D40: Q13485, Q15796, P84022 | E40: PROTEIN COMPLEX | F40: T2, T3, T4 | G40: ChEMBL, STRING | H40: 6.1 | I40: 0.4375 | K40: Alzheimer's Disease
A41: CPX-98 | B41: cathepsin b (ctsb) | C41: CTSB,CSTA | D41: P07858, P01040 | E41: PROTEIN COMPLEX | F41: T2, T3, T4 | G41: STRING, TTD | H41: 6.1 | I41: 0.4375 | K41: Alzheimer's Disease
A42: CPX-674 | B42: calmodulin-3 | C42: calm_human,PPP3CA,PPP3R1,AKAP5 | D42: P62158, Q08209, P63098, P24588 | E42: PROTEIN COMPLEX | F42: T2, T3, T4 | G42: ChEMBL, STRING | H42: 6.1 | I42: 0.4375 | K42: Alzheimer's Disease
A43: CPX-880 | B43: brd4/hdac1 | C43: GATAD2A,GATAD2B,CHD4,CHD3,MTA1,MTA2,MTA3,HDAC1,HDAC2,RBBP4,RBBP7,MBD2 | D43: Q86YP4, Q8WXI9, Q14839, Q12873, Q13330, O94776, Q9BTC8, Q13547, Q92769, Q09028, Q16576, Q9UBB5 | E43: PROTEIN COMPLEX | F43: T2, T3, T4 | G43: ChEMBL, STRING | H43: 6.1 | I43: 0.4375 | K43: Alzheimer's Disease
A44: CPX-900 | B44: ataxin-7 (spinocerebellar ataxia type 7 protein) | C44: SF3B3,SF3B5,SUPT3H,TRRAP,KAT2A,TAF6L,TAF5L,SUPT7L,TADA3,TADA1,TAF9,TAF10,TAF12,ATXN7L3,USP22,ENY2,ATXN7,SUPT20H,SGF29,TADA2B | D44: Q15393, Q9BWJ5, O75486, Q9Y4A5, Q92830, Q9Y6J9, O75529, O94864, O75528, Q96BN2, Q16594, Q12962, Q16514, Q14CW9, Q9UPT9, Q9NPA8, O15265, Q8NEM7, Q96ES7, Q86TJ2 | E44: PROTEIN COMPLEX | F44: T2, T3, T4 | G44: ChEMBL, STRING | H44: 6.1 | I44: 0.4375 | K44: Alzheimer's Disease
A45: CPX-903 | B45: ataxin-7 (spinocerebellar ataxia type 7 protein) | C45: SUPT3H,KAT2A,TADA3,TAF10,TAF12,TAF5L,TAF9,TRRAP,TAF7,TAF6,TAF5,TAF4,TAF2,ATXN7L3,ATXN7,USP22,ENY2 | D45: O75486, Q92830, O75528, Q12962, Q16514, O75529, Q16594, Q9Y4A5, Q15545, P49848, Q15542, O00268, Q6P1X5, Q14CW9, O15265, Q9UPT9, Q9NPA8 | E45: PROTEIN COMPLEX | F45: T2, T3, T4 | G45: ChEMBL, STRING | H45: 6.1 | I45: 0.4375 | K45: Alzheimer's Disease
A46: CPX-922 | B46: brd4/hdac1 | C46: GATAD2A,GATAD2B,CHD4,CHD3,MTA1,MTA2,MTA3,HDAC1,HDAC2,RBBP4,RBBP7,MBD3 | D46: Q86YP4, Q8WXI9, Q14839, Q12873, Q13330, O94776, Q9BTC8, Q13547, Q92769, Q09028, Q16576, O95983 | E46: PROTEIN COMPLEX | F46: T2, T3, T4 | G46: ChEMBL, STRING | H46: 6.1 | I46: 0.4375 | K46: Alzheimer's Disease
A47: CPX-997 | B47: histone acetyltransferase gcn5 | C47: KAT2A,TADA3,SGF29,YEATS2,ZZZ3,KAT14,MBIP,WDR5,DR1,TADA2A | D47: Q92830, O75528, Q96ES7, Q9ULM3, Q8IYH5, Q9H8E8, Q9NS73, P61964, Q01658, O75478 | E47: PROTEIN COMPLEX | F47: T2, T3, T4 | G47: ChEMBL, STRING | H47: 6.1 | I47: 0.4375 | K47: Alzheimer's Disease
A48: CPX-1003 | B48: calmodulin-3 | C48: PPP3CA,PPP3R1,calm_human | D48: Q08209, P63098, P62158 | E48: PROTEIN COMPLEX | F48: T2, T3, T4 | G48: ChEMBL, STRING | H48: 6.1 | I48: 0.4375 | K48: Alzheimer's Disease
A49: CPX-1017 | B49: cytochrome b-245 heavy chain (ec 1.-.-.-) (cgd91-phox) (cytochrome b(558) subunit beta) (cytochrome b558 subunit beta) (heme-binding membrane glycoprotein gp91phox) (nadph oxidase 2) (neutrophil cytochrome b 91 kda polypeptide) (superoxide-generating nadph oxidase heavy chain subunit) (gp91-1) (gp91-phox) (p22 phagocyte b-cytochrome) | C49: CYBA,NCF1,NCF4,NCF2,CYBB,RAC1 | D49: P13498, P14598, Q15080, P19878, P04839, P63000 | E49: PROTEIN COMPLEX | F49: T2, T3, T4 | G49: ChEMBL, STRING, TTD | H49: 6.1 | I49: 0.4375 | K49: Alzheimer's Disease
A50: CPX-1048 | B50: calmodulin-3 | C50: PPP3CA,PPP3R2,calm_human | D50: Q08209, Q96LZ3, P62158 | E50: PROTEIN COMPLEX | F50: T2, T3, T4 | G50: ChEMBL, STRING | H50: 6.1 | I50: 0.4375 | K50: Alzheimer's Disease
A51: CPX-1114 | B51: calmodulin-3 | C51: calm_human,PPP3CA,PPP3R2,AKAP5 | D51: P62158, Q08209, Q96LZ3, P24588 | E51: PROTEIN COMPLEX | F51: T2, T3, T4 | G51: ChEMBL, STRING | H51: 6.1 | I51: 0.4375 | K51: Alzheimer's Disease
... A67: CPX-6062 | B67: homeobox protein nkx-2.1 (homeobox protein nk-2 homolog a) (thyroid nuclear factor 1) (thyroid transcription factor 1) (ttf-1) (thyroid-specific enhancer-binding protein) (t/ebp) | C67: SMAD3,NKX2-1 | D67: P84022, P43699 | E67: PROTEIN COMPLEX | F67: T2, T3, T4 | G67: ChEMBL, STRING | H67: 6.1 | I67: 0.4375 | K67: Alzheimer's Disease
A68: ABCB11 | B68: bile salt export pump | D68: O95342 | E68: SINGLE PROTEIN | F68: T2, T3 | G68: ChEMBL | H68: 6 | I68: 0.431875 | K68: Alzheimer's Disease
A69: ABCC2 | B69: canalicular multispecific organic anion transporter 1 | D69: Q92887 | E69: SINGLE PROTEIN | F69: T2, T3 | G69: ChEMBL | H69: 6 | I69: 0.431875 | K69: Alzheimer's Disease
A70: ABCC3 | B70: canalicular multispecific organic anion transporter 2 | D70: O15438 | E70: SINGLE PROTEIN | F70: T2, T3 | G70: ChEMBL | H70: 6 | I70: 0.431875 | K70: Alzheimer's Disease
A71: ABCC4 | B71: multidrug resistance-associated protein 4 | D71: O15439 | E71: SINGLE PROTEIN | F71: T2, T3 | G71: ChEMBL | H71: 6 | I71: 0.431875 | K71: Alzheimer's Disease
A72: ADORA1 | B72: adenosine a1 receptor | D72: P30542 | E72: SINGLE PROTEIN | F72: T2, T3 | G72: ChEMBL | H72: 6 | I72: 0.431875 | K72: Alzheimer's Disease
A73: ADORA2A | B73: adenosine a2a receptor | D73: P29274 | E73: SINGLE PROTEIN | F73: T2, T3 | G73: ChEMBL, TTD | H73: 6 | I73: 0.431875 | K73: Alzheimer's Disease
A74: ADORA3 | B74: adenosine a3 receptor | D74: P0DMS8 | E74: SINGLE PROTEIN | F74: T2, T3 | G74: ChEMBL | H74: 6 | I74: 0.431875 | K74: Alzheimer's Disease
A75: ADRA1A | B75: alpha-1a adrenergic receptor | D75: P35348 | E75: SINGLE PROTEIN | F75: T2, T3 | G75: ChEMBL | H75: 6 | I75: 0.431875 | K75: Alzheimer's Disease
A76: ADRA1D | B76: alpha-1d adrenergic receptor | D76: P25100 | E76: SINGLE PROTEIN | F76: T2, T3 | G76: ChEMBL | H76: 6 | I76: 0.431875 | K76: Alzheimer's Disease
A77: ADRA2A | B77: alpha-2a adrenergic receptor | D77: P08913 | E77: SINGLE PROTEIN | F77: T2, T3 | G77: ChEMBL | H77: 6 | I77: 0.431875 | K77: Alzheimer's Disease
A78: ADRA2B | B78: alpha-2b adrenergic receptor | D78: P18089 | E78: SINGLE PROTEIN | F78: T2, T3 | G78: ChEMBL | H78: 6 | I78: 0.431875 | K78: Alzheimer's Disease
A79: ADRA2C | B79: adrenergic receptor alpha-2c (adra2c) | D79: P18825 | E79: SINGLE PROTEIN | F79: T2, T3 | G79: ChEMBL, TTD | H79: 6 | I79: 0.431875 | K79: Alzheimer's Disease
... A107: CNR1 | B107: cannabinoid cb1 receptor | D107: P21554 | E107: SINGLE PROTEIN | F107: T2, T3 | G107: ChEMBL | H107: 6 | I107: 0.431875 | K107: Alzheimer's Disease
A108: CPX-12 | B108: mothers against decapentaplegic homolog 3 | C108: SMAD3 | D108: P84022 | E108: PROTEIN COMPLEX | F108: T2, T3 | G108: ChEMBL | H108: 6 | I108: 0.431875 | K108: Alzheimer's Disease
A109: CPX-236 | B109: neuronal acetylcholine receptor alpha-7 (chrna7) | C109: P36544-PRO_0000000366 | D109: P36544 | E109: PROTEIN COMPLEX | F109: T2, T3 | G109: ChEMBL, TTD | H109: 6 | I109: 0.431875 | K109: Alzheimer's Disease
A110: CPX-240 | B110: integrin alpha-5/neuronal acetylcholine receptor subunit alpha-3/neuronal acetylcholine receptor subunit beta-2/neuronal acetylcholine receptor subunit beta-4 | C110: P17787-PRO_0000000379,P36544-PRO_0000000366 | D110: P17787, P36544 | E110: PROTEIN COMPLEX | F110: T2, T3 | G110: ChEMBL, TTD | H110: 6 | I110: 0.431875 | K110: Alzheimer's Disease
A111: CPX-271 | B111: serotonin 3a (5-ht3a) receptor | C111: HTR3A,HTR3B | D111: P46098, O95264 | E111: PROTEIN COMPLEX | F111: T2, T3 | G111: ChEMBL | H111: 6 | I111: 0.431875 | K111: Alzheimer's Disease
A112: CPX-272 | B112: serotonin 3a (5-ht3a) receptor | C112: HTR3D,HTR3A | D112: Q70Z44, P46098 | E112: PROTEIN COMPLEX | F112: T2, T3 | G112: ChEMBL | H112: 6 | I112: 0.431875 | K112: Alzheimer's Disease
A113: CPX-273 | B113: serotonin 3a (5-ht3a) receptor | C113: HTR3E,HTR3A | D113: A5X5Y0, P46098 | E113: PROTEIN COMPLEX | F113: T2, T3 | G113: ChEMBL | H113: 6 | I113: 0.431875 | K113: Alzheimer's Disease
A114: CPX-276 | B114: serotonin 3a (5-ht3a) receptor | C114: HTR3C,HTR3A | D114: Q8WXA8, P46098 | E114: PROTEIN COMPLEX | F114: T2, T3 | G114: ChEMBL | H114: 6 | I114: 0.431875 | K114: Alzheimer's Disease
A115: CPX-480 | B115: proto-oncogene c-jun | C115: JUN,NFATC2,FOS | D115: P05412, Q13469, P01100 | E115: PROTEIN COMPLEX | F115: T2, T3 | G115: ChEMBL | H115: 6 | I115: 0.431875 | K115: Alzheimer's Disease
A116: CPX-486 | B116: proto-oncogene c-jun | C116: JUN,FOS | D116: P05412, P01100 | E116: PROTEIN COMPLEX | F116: T2, T3 | G116: ChEMBL | H116: 6 | I116: 0.431875 | K116: Alzheimer's Disease
A117: CPX-490 | B117: proto-oncogene c-jun | C117: JUN | D117: P05412 | E117: PROTEIN COMPLEX | F117: T2, T3 | G117: ChEMBL | H117: 6 | I117: 0.431875 | K117: Alzheimer's Disease
A118: CPX-654 | B118: nuclear receptor subfamily 4 group a member 2/retinoic acid receptor rxr-alpha | C118: RXRA,THRB | D118: P19793, P10828 | E118: PROTEIN COMPLEX | F118: T2, T3 | G118: ChEMBL | H118: 6 | I118: 0.431875 | K118: Alzheimer's Disease
A119: CPX-952 | B119: caspase-1 | C119: P29466-PRO_0000004522,P29466-PRO_0000004524 | D119: P29466, P29466 | E119: PROTEIN COMPLEX | F119: T2, T3 | G119: ChEMBL | H119: 6 | I119: 0.431875 | K119: Alzheimer's Disease
... A154: CPX-8579 | B154: gaba receptor beta-3 subunit | C154: GABRA3,GABRB3,GABRG3 | D154: P34903, P28472, Q99928 | E154: PROTEIN COMPLEX | F154: T2, T3 | G154: ChEMBL, TTD | H154: 6 | I154: 0.431875 | K154: Alzheimer's Disease
A155: CTRC | B155: chymotrypsin c | D155: Q99895 | E155: SINGLE PROTEIN | F155: T2, T3 | G155: ChEMBL | H155: 6 | I155: 0.431875 | K155: Alzheimer's Disease
A156: CTSG | B156: cathepsin g | D156: P08311 | E156: SINGLE PROTEIN | F156: T2, T3 | G156: ChEMBL | H156: 6 | I156: 0.431875 | K156: Alzheimer's Disease
A157: CTSL | B157: cathepsin l | D157: P07711 | E157: SINGLE PROTEIN | F157: T2, T3 | G157: ChEMBL, TTD | H157: 6 | I157: 0.431875 | K157: Alzheimer's Disease
A158: CXCL8 | B158: interleukin-8 | D158: P10145 | E158: SINGLE PROTEIN | F158: T2, T3 | G158: ChEMBL | H158: 6 | I158: 0.431875 | K158: Alzheimer's Disease
A159: CXCR1 | B159: interleukin-8 receptor a | D159: P25024 | E159: SINGLE PROTEIN | F159: T2, T3 | G159: ChEMBL | H159: 6 | I159: 0.431875 | K159: Alzheimer's Disease
A160: CXCR2 | B160: interleukin-8 receptor b | D160: P25025 | E160: SINGLE PROTEIN | F160: T2, T3 | G160: ChEMBL | H160: 6 | I160: 0.431875 | K160: Alzheimer's Disease
A161: CYP1A2 | B161: cytochrome p450 1a2 | D161: P05177 | E161: SINGLE PROTEIN | F161: T2, T3 | G161: ChEMBL | H161: 6 | I161: 0.431875 | K161: Alzheimer's Disease
A162: CYP2A6 | B162: cytochrome p450 2a6 | D162: P11509 | E162: SINGLE PROTEIN | F162: T2, T3 | G162: ChEMBL | H162: 6 | I162: 0.431875 | K162: Alzheimer's Disease
A163: CYP2B6 | B163: cytochrome p450 2b6 | D163: P20813 | E163: SINGLE PROTEIN | F163: T2, T3 | G163: ChEMBL | H163: 6 | I163: 0.431875 | K163: Alzheimer's Disease
A164: CYP2C8 | B164: cytochrome p450 2c8 | D164: P10632 | E164: SINGLE PROTEIN | F164: T2, T3 | G164: ChEMBL | H164: 6 | I164: 0.431875 | K164: Alzheimer's Disease
A165: CYP2C9 | B165: cytochrome p450 2c9 | D165: P11712 | E165: SINGLE PROTEIN | F165: T2, T3 | G165: ChEMBL | H165: 6 | I165: 0.431875 | K165: Alzheimer's Disease
A166: CYP2C19 | B166: cytochrome p450 2c19 | D166: P33261 | E166: SINGLE PROTEIN | F166: T2, T3 | G166: ChEMBL | H166: 6 | I166: 0.431875 | K166: Alzheimer's Disease
... A267: VIPR1 | B267: vasoactive intestinal polypeptide receptor 1 | D267: P32241 | E267: SINGLE PROTEIN | F267: T2, T3 | G267: ChEMBL | H267: 6 | I267: 0.431875 | K267: Alzheimer's Disease
A268: CPX-91 | B268: myc proto-oncogene protein | C268: MAX,MYC | D268: P61244, P01106 | E268: PROTEIN COMPLEX | F268: T2, T4 | G268: ChEMBL, STRING | H268: 5.1 | I268: 0.38125 | K268: Alzheimer's Disease
A269: CPX-117 | B269: filamin a (flna) | C269: FLNA,GP1BA,GP1BB,GP9,GP5 | D269: P21333, P07359, P13224, P14770, P40197 | E269: PROTEIN COMPLEX | F269: T2, T4 | G269: STRING, TTD | H269: 5.1 | I269: 0.38125 | K269: Alzheimer's Disease
A270: CPX-265 | B270: h/aca ribonucleoprotein complex subunit 2 (nucleolar protein family a member 2) (snornp protein nhp2) | C270: NOP10,NHP2,TERT,GAR1,DKC1,WRAP53 | D270: Q9NPE3, Q9NX24, O14746, Q9NY12, O60832, Q9BUR4 | E270: PROTEIN COMPLEX | F270: T2, T4 | G270: ChEMBL, STRING | H270: 5.1 | I270: 0.38125 | K270: Alzheimer's Disease
A271: CPX-308 | B271: crl4(crbn) e3 ubiquitin ligase | C271: DDB1,DDB2 | D271: Q16531, Q92466 | E271: PROTEIN COMPLEX | F271: T2, T4 | G271: ChEMBL, STRING | H271: 5.1 | I271: 0.38125 | K271: Alzheimer's Disease
A272: CPX-469 | B272: lethal(3)malignant brain tumor-like protein 1 | C272: CBX3,L3MBTL1,RB1 | D272: Q13185, Q9Y468, P06400 | E272: PROTEIN COMPLEX | F272: T2, T4 | G272: ChEMBL, STRING | H272: 5.1 | I272: 0.38125 | K272: Alzheimer's Disease
A273: CPX-477 | B273: crl4(crbn) e3 ubiquitin ligase | C273: DDB2,RBX1,CUL4A,DDB1 | D273: Q92466, P62877, Q13619, Q16531 | E273: PROTEIN COMPLEX | F273: T2, T4 | G273: ChEMBL, STRING | H273: 5.1 | I273: 0.38125 | K273: Alzheimer's Disease
A274: CPX-494 | B274: plasminogen activator inhibitor (pai) | C274: SERPINE1,PLAT | D274: P05121, P00750 | E274: PROTEIN COMPLEX | F274: T2, T4 | G274: ChEMBL, STRING, TTD | H274: 5.1 | I274: 0.38125 | K274: Alzheimer's Disease
A275: CPX-513 | B275: nuclear receptor coactivator 2 (ncoa-2) (class e basic helix-loop-helix protein 75) (bhlhe75) (transcriptional intermediary factor 2) (htif2) | C275: NCOA2,RXRA | D275: Q15596, P19793 | E275: PROTEIN COMPLEX | F275: T2, T4 | G275: ChEMBL, STRING | H275: 5.1 | I275: 0.38125 | K275: Alzheimer's Disease
A276: CPX-514 | B276: myc box-dependent-interacting protein 1 (amphiphysin ii) (amphiphysin-like protein) (box-dependent myc-interacting protein 1) (bridging integrator 1) | C276: BIN1,MYC | D276: O00499, P01106 | E276: PROTEIN COMPLEX | F276: T2, T4 | G276: ChEMBL, STRING | H276: 5.1 | I276: 0.38125 | K276: Alzheimer's Disease
...

Sheet T4_metrics
A1: Nombre proteína | B1: Target_group | C1: Cluster_label | D1: intracluster connect | E1: intercluster connect | F1: Conectivity_Score | G1: Termino GO
A2: CPX-1209 | B2: T4 | C2: 10 | D2: 39.226 | E2: 169.223 | F2: 1.3194661 | G2: nBAF Complex
A3: CPX-1216 | B3: T4 | C3: 10 | D3: 39.226 | E3: 169.223 | F3: 1.4328376 | G3: nBAF Complex
A4: CPX-1219 | B4: T4 | C4: 10 | D4: 39.226 | E4: 169.223 | F4: 1.3189422 | G4: nBAF Complex
A5: CPX-1226 | B5: T4 | C5: 10 | D5: 39.226 | E5: 169.223 | F5: 1.3194661 | G5: nBAF Complex
A6: CPX-1202 | B6: T4 | C6: 10 | D6: 39.644 | E6: 169.114 | F6: 1.4178513 | G6: nBAF Complex
A7: CPX-1203 | B7: T4 | C7: 10 | D7: 39.644 | E7: 169.114 | F7: 1.3051482 | G7: nBAF Complex
A8: CPX-1207 | B8: T4 | C8: 10 | D8: 39.644 | E8: 169.114 | F8: 1.3056945 | G8: nBAF Complex
A9: CPX-1225 | B9: T4 | C9: 10 | D9: 39.644 | E9: 169.114 | F9: 1.3056945 | G9: nBAF Complex
A10: CPX-1195 | B10: T4 | C10: 10 | D10: 39.226 | E10: 168.796 | F10: 1.2518859 | G10: nBAF Complex
A11: CPX-1204 | B11: T4 | C11: 10 | D11: 39.226 | E11: 168.774 | F11: 1.1963229 | G11: nBAF Complex
A12: CPX-1212 | B12: T4 | C12: 10 | D12: 39.226 | E12: 168.774 | F12: 1.1958308 | G12: nBAF Complex
A13: CPX-1222 | B13: T4 | C13: 10 | D13: 39.226 | E13: 168.774 | F13: 0.94145284 | G13: nBAF Complex
... A693: CPX-8641 | B693: T4 | C693: 5 | D693: 145.803 | E693: 0 | F693: 0.89132601 | G693: Anterograde Trans-Synaptic Signaling
